neon_wave/__init__.py
neon_wave/effects-toggle.html
neon_wave/layout.html
neon_wave/sidebar.html
neon_wave/theme-toggle.html
neon_wave/theme.conf
neon_wave/static/css/code-blocks.css
neon_wave/static/css/components.css
neon_wave/static/css/neon-wave.css
neon_wave/static/css/responsive.css
neon_wave/static/fonts/.gitkeep
neon_wave/static/fonts/audiowide.css
neon_wave/static/fonts/bungee.css
neon_wave/static/fonts/intel-one-mono.css
neon_wave/static/fonts/monoton.css
neon_wave/static/fonts/orbitron.css
neon_wave/static/fonts/press-start-2p.css
neon_wave/static/fonts/share-tech-mono.css
neon_wave/static/fonts/syncopate.css
neon_wave/static/js/neon-wave.js
neon_wave/static/js/theme-toggle.js
neon_wave-1.0.1.dist-info/METADATA
neon_wave-1.0.1.dist-info/WHEEL
neon_wave-1.0.1.dist-info/entry_points.txt
neon_wave-1.0.1.dist-info/licenses/LICENSE
neon_wave-1.0.1.dist-info/RECORD
